distanceclosure/__init__.py
distanceclosure/backbone.py
distanceclosure/closure.py
distanceclosure/dijkstra.py
distanceclosure/distance.py
distanceclosure/utils.py
distanceclosure-0.5.dist-info/WHEEL
distanceclosure-0.5.dist-info/METADATA
distanceclosure-0.5.dist-info/RECORD
