Metadata-Version: 2.1
Name: distanceclosure
Version: 0.5
Summary: Distance Closure on Complex Networks
Author-email: Rion Brattig Correia <rionbr@gmail.com>, Felipe Xavier Costa <fcosta@binghamton.edu>
Requires-Python: >=3.6
Classifier: Development Status :: 4 - Beta
Classifier: License :: OSI Approved :: MIT License
Classifier: Programming Language :: Python :: 3.6
Classifier: Intended Audience :: Science/Research
Classifier: Topic :: Scientific/Engineering :: Information Analysis
Requires-Dist: numpy>=1.21
Requires-Dist: scipy>=1.7
Requires-Dist: networkx>=2.1
Requires-Dist: pandas>=0.25
